protonn/__init__.py
protonn/_version.py
protonn/config.py
protonn/debug.py
protonn/experiment.py
protonn/experiment_config.py
protonn/stats.py
protonn/data/__init__.py
protonn/data/imaging/__init__.py
protonn/data/imaging/misc.py
protonn/distributed/__init__.py
protonn/distributed/horovod_adapter.py
protonn/distributed/run_ddp.py
protonn/distributed/torch_distributed_adapter.py
protonn/frameworks/__init__.py
protonn/frameworks/chainer/__init__.py
protonn/frameworks/chainer/misc.py
protonn/frameworks/chainer/snapshot_best.py
protonn/frameworks/chainer/triggers.py
protonn/parameters/__init__.py
protonn/parameters/core.py
protonn/pl/__init__.py
protonn/pl/cluster_mpi.py
protonn/pl/model_base.py
protonn/pl/threaded_iterator.py
protonn/pl/trainer.py
protonn/scheduling/__init__.py
protonn/utils/__init__.py
protonn/utils/test_json.py
protonn/vis/__init__.py
protonn/vis/lines.py
protonn/vis/styles.py
protonn/vis/vis.py
protonn-0.4.2.dist-info/LICENSE
protonn-0.4.2.dist-info/METADATA
protonn-0.4.2.dist-info/WHEEL
protonn-0.4.2.dist-info/top_level.txt
protonn-0.4.2.dist-info/RECORD
