Metadata-Version: 2.1
Name: protonn
Version: 0.4.2
License-File: LICENSE
Requires-Dist: numpy
Requires-Dist: pandas
Requires-Dist: static-typing
Requires-Dist: typed-ast
Requires-Dist: typed-astunparse
